<?xml version="1.0" encoding="ISO-8859-1" ?>
<!DOCTYPE romeoapi SYSTEM "http://www.sherpa.ac.uk/romeo/romeoapi24.dtd">
<!-- from http://www.sherpa.ac.uk/romeo/SHERPA%20RoMEO%20API%20V-2-4%202009-10-29.pdf -->
<romeoapi version="2.4.2">
  <header>
    <parameters>
      <parameter source="specified">
        <parametername>id</parametername>
        <parametervalue>3</parametervalue>
      </parameter>
      <parameter source="default">
        <parametername>showfunder</parametername>
        <parametervalue>none</parametervalue>
      </parameter>
      <parameter source="default">
        <parametername>fIDnum</parametername>
        <parametervalue>|</parametervalue>
      </parameter>
    </parameters>
    <numhits>1</numhits>
    <apicontrol>identifier</apicontrol>
    <outcome>publisherFound</outcome>
    <message/>
    <licence>SHERPA/RoMEO data is available for re-use under a Creative Commons Attribution-Non-Commercial-Share Alike 2.5 licence. For more details, please see the 'conditions for re-use' at the &lt;licenceurl /&gt;, and linked-to from the SHERPA/RoMEO home page.</licence>
    <licenceurl>http://www.sherpa.ac.uk/romeoreuse.html</licenceurl>
    <disclaimer>All SHERPA/RoMEO information is correct to the best of our knowledge but should not be relied upon for legal advice. SHERPA cannot be held responsible for the re-use of RoMEO data, or for alternative interpretations which are derived from this information.</disclaimer>
    <timestamp>03-Jun-2009:13:21:13</timestamp>
  </header>
  <journals/>
  <publishers>
    <publisher id="3">
      <name>American Association for the Advancement of Science</name>
      <alias/>
      <homeurl>http://www.aaas.org/</homeurl>
      <preprints>
        <prearchiving>can</prearchiving>
        <prerestrictions/>
      </preprints>
      <postprints>
        <postarchiving>can</postarchiving>
        <postrestrictions/>
      </postprints>
      <conditions>
        <condition>Pre-print may be considered prior publication</condition>
        <condition>Pre-print on not-for-profit preprint servers where allowed, please contact editors for clarification</condition>
        <condition>Cannot archive until publication</condition>
        <condition>On author's personal web site</condition>
        <condition>Author's own version of accepted paper</condition>
        <condition>Must link to publisher version</condition>
        <condition>Published source must be acknowledged</condition>
        <condition>Authors covered by funding agency rules, may post authors own version in PubMed Central after a 6 month embargo</condition>
        <condition>Authors covered by funding agency rules, must state on submission, for article to be released in PubMed Central after 6 months after publication.</condition>
      </conditions>
      <mandates/>
      <paidaccess>
        <paidaccessurl/>
        <paidaccessname/>
        <paidaccessnotes/>
      </paidaccess>
      <copyrightlinks>
        <copyrightlink>
          <copyrightlinktext>License to Publish -- Information for Authors</copyrightlinktext>
          <copyrightlinkurl>http://www.sciencemag.org/feature/contribinfo/prep/lic_info.pdf
          </copyrightlinkurl>
        </copyrightlink>
        <copyrightlink>
          <copyrightlinktext>License to Publish Form</copyrightlinktext>
          <copyrightlinkurl>http://www.sciencemag.org/feature/contribinfo/prep/license.pdf
          </copyrightlinkurl>
        </copyrightlink>
        <copyrightlink>
          <copyrightlinktext>Pmc Policy</copyrightlinktext>
          <copyrightlinkurl>http://www.sciencemag.org/help/authors/pmc.dtl</copyrightlinkurl>
        </copyrightlink>
        <copyrightlink>
          <copyrightlinktext>Pre-print Comment</copyrightlinktext>
          <copyrightlinkurl>http://www.sciencemag.org/about/authors/faq/index.dtl#prioronline_faq</copyrightlinkurl>
        </copyrightlink>
      </copyrightlinks>
      <romeocolour>green</romeocolour>
      <dateadded>2004-01-10 00:00:00</dateadded>
      <dateupdated>2009-01-27 13:46:21</dateupdated>
    </publisher>
  </publishers>
</romeoapi>
